textual_universal_directorytree/__about__.py
textual_universal_directorytree/__init__.py
textual_universal_directorytree/__main__.py
textual_universal_directorytree/alternate_paths.py
textual_universal_directorytree/app.py
textual_universal_directorytree/py.typed
textual_universal_directorytree/universal_directory_tree.py
textual_universal_directorytree/utils.py
textual_universal_directorytree-1.7.0.dist-info/METADATA
textual_universal_directorytree-1.7.0.dist-info/WHEEL
textual_universal_directorytree-1.7.0.dist-info/licenses/LICENSE
textual_universal_directorytree-1.7.0.dist-info/RECORD
