Metadata-Version: 2.4
Name: textual-universal-directorytree
Version: 1.7.0
Summary: A Textual Directory Tree for all File Systems
Project-URL: Documentation, https://github.com/juftin/textual-universal-directorytree#readme
Project-URL: Issues, https://github.com/juftin/textual-universal-directorytree/issues
Project-URL: Source, https://github.com/juftin/textual-universal-directorytree
Author-email: Justin Flannery <juftin@juftin.com>
License-Expression: MIT
License-File: LICENSE
Keywords: fsspec,plugin,textual,tui
Classifier: Development Status :: 4 - Beta
Classifier: Operating System :: OS Independent
Classifier: Programming Language :: Python
Classifier: Programming Language :: Python :: 3.9
Classifier: Programming Language :: Python :: 3.10
Classifier: Programming Language :: Python :: 3.11
Classifier: Programming Language :: Python :: 3.12
Classifier: Programming Language :: Python :: 3.13
Classifier: Programming Language :: Python :: Implementation :: CPython
Classifier: Programming Language :: Python :: Implementation :: PyPy
Requires-Python: <4,>=3.9
Requires-Dist: textual>=3.0.0
Requires-Dist: universal-pathlib>=0.2.6
Provides-Extra: remote
Requires-Dist: adlfs; extra == 'remote'
Requires-Dist: aiohttp; extra == 'remote'
Requires-Dist: gcsfs; extra == 'remote'
Requires-Dist: paramiko; extra == 'remote'
Requires-Dist: requests>=2; extra == 'remote'
Requires-Dist: s3fs; extra == 'remote'
